mockserial/__init__.py
mockserial/mock_serial.py
pyserial_mock-0.0.1.dist-info/licenses/LICENSE
pyserial_mock-0.0.1.dist-info/METADATA
pyserial_mock-0.0.1.dist-info/WHEEL
pyserial_mock-0.0.1.dist-info/top_level.txt
pyserial_mock-0.0.1.dist-info/RECORD
